discord/__init__.py
discord/calls.py
discord/channel.py
discord/client.py
discord/colour.py
discord/compat.py
discord/embeds.py
discord/emoji.py
discord/enums.py
discord/errors.py
discord/game.py
discord/gateway.py
discord/http.py
discord/invite.py
discord/iterators.py
discord/member.py
discord/message.py
discord/mixins.py
discord/object.py
discord/opus.py
discord/permissions.py
discord/reaction.py
discord/role.py
discord/server.py
discord/state.py
discord/user.py
discord/utils.py
discord/voice_client.py
discord/bin/libopus-0.x64.dll
discord/bin/libopus-0.x86.dll
discord/ext/commands/__init__.py
discord/ext/commands/bot.py
discord/ext/commands/context.py
discord/ext/commands/converter.py
discord/ext/commands/cooldowns.py
discord/ext/commands/core.py
discord/ext/commands/errors.py
discord/ext/commands/formatter.py
discord/ext/commands/view.py
discordpy_legacy-0.16.13.dist-info/LICENSE
discordpy_legacy-0.16.13.dist-info/METADATA
discordpy_legacy-0.16.13.dist-info/WHEEL
discordpy_legacy-0.16.13.dist-info/top_level.txt
discordpy_legacy-0.16.13.dist-info/RECORD
